aicrowd/__init__.py
aicrowd/cli.py
aicrowd/constants.py
aicrowd/errors.py
aicrowd/exceptions.py
aicrowd/magic.py
aicrowd/version.py
aicrowd/auth/__init__.py
aicrowd/auth/exceptions.py
aicrowd/auth/helpers.py
aicrowd/auth/login.py
aicrowd/auth/url_login.py
aicrowd/challenge/__init__.py
aicrowd/challenge/exceptions.py
aicrowd/challenge/helpers.py
aicrowd/challenge/init.py
aicrowd/cmd/__init__.py
aicrowd/cmd/challenge.py
aicrowd/cmd/config.py
aicrowd/cmd/dataset.py
aicrowd/cmd/login.py
aicrowd/cmd/notebook.py
aicrowd/cmd/submission.py
aicrowd/cmd/version.py
aicrowd/config/__init__.py
aicrowd/config/exceptions.py
aicrowd/config/get.py
aicrowd/contexts/__init__.py
aicrowd/contexts/challenge.py
aicrowd/contexts/config.py
aicrowd/contexts/context.py
aicrowd/dataset/__init__.py
aicrowd/dataset/download.py
aicrowd/dataset/exceptions.py
aicrowd/dataset/helpers.py
aicrowd/dataset/list.py
aicrowd/notebook/__init__.py
aicrowd/notebook/clean.py
aicrowd/notebook/exceptions.py
aicrowd/notebook/helpers.py
aicrowd/notebook/split.py
aicrowd/notebook/submit.py
aicrowd/submission/__init__.py
aicrowd/submission/create.py
aicrowd/submission/exceptions.py
aicrowd/submission/helpers.py
aicrowd/utils/__init__.py
aicrowd/utils/git.py
aicrowd/utils/jupyter.py
aicrowd/utils/utils.py
aicrowd_api/__init__.py
aicrowd_api/auth.py
aicrowd_api/challenge.py
aicrowd_api/request.py
aicrowd_api/submission.py
aicrowd_cli-0.1.17.dist-info/METADATA
aicrowd_cli-0.1.17.dist-info/WHEEL
aicrowd_cli-0.1.17.dist-info/entry_points.txt
aicrowd_cli-0.1.17.dist-info/top_level.txt
aicrowd_cli-0.1.17.dist-info/RECORD
